kingdom_sdk/__init__.py
kingdom_sdk/adapters/__init__.py
kingdom_sdk/adapters/message_broker.py
kingdom_sdk/adapters/message_bus.py
kingdom_sdk/adapters/query.py
kingdom_sdk/adapters/repository.py
kingdom_sdk/adapters/unit_of_work.py
kingdom_sdk/config.py
kingdom_sdk/database/__init__.py
kingdom_sdk/database/factories.py
kingdom_sdk/database/mappers.py
kingdom_sdk/database/migrations.py
kingdom_sdk/database/orm.py
kingdom_sdk/database/types.py
kingdom_sdk/domain/__init__.py
kingdom_sdk/domain/aggregate.py
kingdom_sdk/domain/entity.py
kingdom_sdk/domain/exception.py
kingdom_sdk/domain/message.py
kingdom_sdk/domain/value_object.py
kingdom_sdk/ports/__init__.py
kingdom_sdk/ports/message_broker.py
kingdom_sdk/ports/message_bus.py
kingdom_sdk/ports/query.py
kingdom_sdk/ports/repository.py
kingdom_sdk/ports/unit_of_work.py
kingdom_sdk/utils/__init__.py
kingdom_sdk/utils/casting.py
kingdom_sdk/utils/files.py
kingdom_sdk/utils/loader.py
kingdom_sdk/utils/serializer.py
kingdom_sdk/utils/time.py
kingdom_sdk-1.0.0.dist-info/LICENSE
kingdom_sdk-1.0.0.dist-info/WHEEL
kingdom_sdk-1.0.0.dist-info/METADATA
kingdom_sdk-1.0.0.dist-info/RECORD
