Metadata-Version: 2.1
Name: kingdom-sdk
Version: 1.0.0
Summary: Library containing the core modules for the kingdom-python-server
License: MIT
Author: William Abreu
Author-email: william@t10.digital
Requires-Python: >=3.9,<4.0
Classifier: License :: OSI Approved :: MIT License
Classifier: Programming Language :: Python :: 3
Classifier: Programming Language :: Python :: 3.10
Classifier: Programming Language :: Python :: 3.9
Requires-Dist: SQLAlchemy (>=1.4.25,<2.0.0)
Requires-Dist: jinjasql (>=0.1.8,<0.2.0)
Requires-Dist: pytz (>=2021.3,<2022.0)
Requires-Dist: redis (>=3.5.3,<4.0.0)
